MANIFEST.in
README.txt
actionbar.panel-configure.zcml
setup.cfg
setup.py
actionbar/__init__.py
actionbar.panel.egg-info/PKG-INFO
actionbar.panel.egg-info/SOURCES.txt
actionbar.panel.egg-info/dependency_links.txt
actionbar.panel.egg-info/entry_points.txt
actionbar.panel.egg-info/namespace_packages.txt
actionbar.panel.egg-info/not-zip-safe
actionbar.panel.egg-info/paster_plugins.txt
actionbar.panel.egg-info/requires.txt
actionbar.panel.egg-info/top_level.txt
actionbar/panel/__init__.py
actionbar/panel/configure.zcml
actionbar/panel/tests.py
actionbar/panel/version.txt
actionbar/panel/browser/__init__.py
actionbar/panel/browser/configure.zcml
actionbar/panel/browser/interfaces.py
actionbar/panel/browser/viewlets.py
actionbar/panel/browser/images/address_book_32.png
actionbar/panel/browser/images/home_32.png
actionbar/panel/browser/images/newspaper_32.png
actionbar/panel/browser/images/page_table_32.png
actionbar/panel/browser/images/tools_32.png
actionbar/panel/browser/images/user_32.png
actionbar/panel/browser/stylesheets/README.txt
actionbar/panel/browser/stylesheets/main.css
actionbar/panel/browser/templates/__init__.py
actionbar/panel/browser/templates/actionbar.pt
actionbar/panel/browser/templates/actionbar_viewlet.pt
actionbar/panel/browser/templates/home_viewlet.pt
actionbar/panel/browser/templates/members_viewlet.pt
actionbar/panel/browser/templates/news_viewlet.pt
actionbar/panel/browser/templates/personalize_viewlet.pt
actionbar/panel/browser/templates/user_viewlet.pt
actionbar/panel/profiles/default/bottom.feeder_various.txt
actionbar/panel/profiles/default/browserlayer.xml
actionbar/panel/profiles/default/cssregistry.xml
actionbar/panel/profiles/default/metadata.xml
actionbar/panel/profiles/default/viewlets.xml
docs/HISTORY.txt
docs/INSTALL.txt
docs/LICENSE.GPL
docs/LICENSE.txt