Metadata-Version: 1.0
Name: actionbar.panel
Version: 1.2
Summary: Provides a (old) facebook style action panel at the bottom of your  Plone site
Home-page: http://plone.org/products/actionbar.panel
Author: JC Brand, Syslab.com GmbH
Author-email: brand@syslab.com
License: GPL
Keywords: plone panel actionbar
Platform: UNKNOWN
Classifier: Framework :: Plone
Classifier: Programming Language :: Python
